model_collaboration/main.py
model_collaboration/data/__init__.py
model_collaboration/data/agieval.json
model_collaboration/data/agieval_tiny.json
model_collaboration/data/alpacaeval.json
model_collaboration/data/arc_challenge.json
model_collaboration/data/bbh.json
model_collaboration/data/blend.json
model_collaboration/data/coconot.json
model_collaboration/data/culturebench.json
model_collaboration/data/eval.py
model_collaboration/data/gpqa_diamond.json
model_collaboration/data/gpqa_extended.json
model_collaboration/data/gpqa_main.json
model_collaboration/data/gsm8k.json
model_collaboration/data/human_interest.json
model_collaboration/data/human_interest_tiny.json
model_collaboration/data/humaneval.json
model_collaboration/data/math.json
model_collaboration/data/mbpp.json
model_collaboration/data/medmcqa.json
model_collaboration/data/medqa.json
model_collaboration/data/mmlu_redux.json
model_collaboration/data/popqa.json
model_collaboration/data/pubmedqa.json
model_collaboration/data/sciencemeter.json
model_collaboration/data/sciriff.json
model_collaboration/data/tablemwp_free_text.json
model_collaboration/data/tablemwp_multiple_choice.json
model_collaboration/data/theoremqa.json
model_collaboration/data/truthfulqa.json
model_collaboration/data/wikidyk.json
model_collaboration/data/wildchat.json
model_collaboration/logs/README.md
model_collaboration/method/__init__.py
model_collaboration/method/api_cascade.py
model_collaboration/method/api_graph_routing.py
model_collaboration/method/api_mentor_collab.py
model_collaboration/method/api_nudging.py
model_collaboration/method/api_prompt_routing.py
model_collaboration/method/api_switch_generation.py
model_collaboration/method/api_trained_router.py
model_collaboration/method/distributed_generation.py
model_collaboration/method/logit_logit_contrastive.py
model_collaboration/method/logit_logit_fusion.py
model_collaboration/method/sample_approach.py
model_collaboration/method/single_model.py
modelco-0.0.1.5.dist-info/licenses/LICENSE
modelco-0.0.1.5.dist-info/METADATA
modelco-0.0.1.5.dist-info/WHEEL
modelco-0.0.1.5.dist-info/entry_points.txt
modelco-0.0.1.5.dist-info/top_level.txt
modelco-0.0.1.5.dist-info/RECORD
