Metadata-Version: 2.4
Name: modelco
Version: 0.0.1.5
Summary: LLM collaboration
Author-email: Shangbin Feng <shangbin@cs.washington.edu>
License-Expression: LGPL-3.0-only
Project-URL: Homepage, https://github.com/BunsenFeng/model_collaboration
Project-URL: Issues, https://github.com/BunsenFeng/model_collaboration/issues
Classifier: Programming Language :: Python :: 3
Requires-Python: >=3.11.13
License-File: LICENSE
Requires-Dist: accelerate==1.6.0
Requires-Dist: aiohttp==3.12.14
Requires-Dist: aiosignal==1.4.0
Requires-Dist: attrs==25.3.0
Requires-Dist: certifi==2025.6.15
Requires-Dist: charset-normalizer==3.4.2
Requires-Dist: datasets==4.0.0
Requires-Dist: dill==0.3.8
Requires-Dist: filelock==3.18.0
Requires-Dist: frozenlist==1.7.0
Requires-Dist: fsspec==2025.3.0
Requires-Dist: huggingface-hub==0.33.1
Requires-Dist: idna==3.10
Requires-Dist: jinja2==3.1.6
Requires-Dist: markupsafe==3.0.2
Requires-Dist: mergekit==0.1.4
Requires-Dist: multidict==6.6.3
Requires-Dist: multiprocess==0.70.16
Requires-Dist: nevergrad
Requires-Dist: numpy==2.3.1
Requires-Dist: openai==1.93.2
Requires-Dist: packaging==25.0
Requires-Dist: pandas==2.3.1
Requires-Dist: pillow==11.2.1
Requires-Dist: protobuf==6.31.1
Requires-Dist: psutil==7.0.0
Requires-Dist: pyarrow==20.0.0
Requires-Dist: python-dateutil==2.9.0.post0
Requires-Dist: pytz==2025.2
Requires-Dist: pyyaml==6.0.2
Requires-Dist: regex==2024.11.6
Requires-Dist: requests==2.32.4
Requires-Dist: safetensors==0.5.3
Requires-Dist: scipy==1.16.1
Requires-Dist: six==1.17.0
Requires-Dist: sympy==1.14.0
Requires-Dist: tenacity==9.1.2
Requires-Dist: tokenizers==0.21.2
Requires-Dist: torch==2.7.1
Requires-Dist: torch-geometric==2.7.0
Requires-Dist: torchaudio==2.7.1
Requires-Dist: torchvision==0.22.1
Requires-Dist: tqdm==4.67.1
Requires-Dist: transformers==4.53.0
Requires-Dist: triton==3.3.1
Requires-Dist: trl==0.19.1
Requires-Dist: typing-extensions==4.14.0
Requires-Dist: typing-inspection==0.4.1
Requires-Dist: urllib3==2.5.0
Requires-Dist: wcwidth==0.2.13
Requires-Dist: xxhash==3.5.0
Requires-Dist: yarl==1.20.1
Dynamic: license-file
